blueshell/__init__.py
blueshell/list.py
blueshell/shell.py
test/__init__.py
blueshell-0.0.7.dist-info/LICENSE
blueshell-0.0.7.dist-info/METADATA
blueshell-0.0.7.dist-info/WHEEL
blueshell-0.0.7.dist-info/top_level.txt
blueshell-0.0.7.dist-info/RECORD
