Metadata-Version: 2.1
Name: blueshell
Version: 0.0.7
Summary: Blue Shell is a chat shell for local ai service endpoint
Home-page: https://github.com/MarchLiu/blue-shell
Author: marsliu
Author-email: Liu Xin <mars.liu@outlook.com>
License: MIT License
Project-URL: Homepage, https://github.com/MarchLiu/blue-shell
Project-URL: Issues, https://github.com/MarchLiu/blue-shell/issues
Classifier: Programming Language :: Python :: 3
Classifier: License :: OSI Approved :: MIT License
Classifier: Operating System :: OS Independent
Requires-Python: >=3.8
License-File: LICENSE
Requires-Dist: requests >=2.31.0
Requires-Dist: prompt-toolkit >=3.0.41
Requires-Dist: rich >=13.7.0
